FruitSpaceAPI.py
fruitspaceapi-0.1.2.dist-info/METADATA
fruitspaceapi-0.1.2.dist-info/WHEEL
fruitspaceapi-0.1.2.dist-info/RECORD
